arraythings/__init__.py
arraythings/array.py
arraythings-0.1.0.dist-info/LICENSE
arraythings-0.1.0.dist-info/METADATA
arraythings-0.1.0.dist-info/WHEEL
arraythings-0.1.0.dist-info/top_level.txt
arraythings-0.1.0.dist-info/RECORD
